glodap/__init__.py
glodap-0.3.dist-info/licenses/LICENSE
glodap-0.3.dist-info/METADATA
glodap-0.3.dist-info/WHEEL
glodap-0.3.dist-info/top_level.txt
glodap-0.3.dist-info/RECORD
